groupdocs/__init__.py
groupdocs/pycore.cp310-win32.pyd
groupdocs/pycore.cp311-win32.pyd
groupdocs/pycore.cp35-win32.pyd
groupdocs/pycore.cp36-win32.pyd
groupdocs/pycore.cp37-win32.pyd
groupdocs/pycore.cp38-win32.pyd
groupdocs/pycore.cp39-win32.pyd
groupdocs/pydrawing.cp310-win32.pyd
groupdocs/pydrawing.cp311-win32.pyd
groupdocs/pydrawing.cp35-win32.pyd
groupdocs/pydrawing.cp36-win32.pyd
groupdocs/pydrawing.cp37-win32.pyd
groupdocs/pydrawing.cp38-win32.pyd
groupdocs/pydrawing.cp39-win32.pyd
groupdocs/pygc.cp310-win32.pyd
groupdocs/pygc.cp311-win32.pyd
groupdocs/pygc.cp35-win32.pyd
groupdocs/pygc.cp36-win32.pyd
groupdocs/pygc.cp37-win32.pyd
groupdocs/pygc.cp38-win32.pyd
groupdocs/pygc.cp39-win32.pyd
groupdocs/pyreflection.cp310-win32.pyd
groupdocs/pyreflection.cp311-win32.pyd
groupdocs/pyreflection.cp35-win32.pyd
groupdocs/pyreflection.cp36-win32.pyd
groupdocs/pyreflection.cp37-win32.pyd
groupdocs/pyreflection.cp38-win32.pyd
groupdocs/pyreflection.cp39-win32.pyd
groupdocs/viewer.cp310-win32.pyd
groupdocs/viewer.cp311-win32.pyd
groupdocs/viewer.cp35-win32.pyd
groupdocs/viewer.cp36-win32.pyd
groupdocs/viewer.cp37-win32.pyd
groupdocs/viewer.cp38-win32.pyd
groupdocs/viewer.cp39-win32.pyd
groupdocs/__pyinstaller/__init__.pyi
groupdocs/__pyinstaller/hook-groupdocs.py
groupdocs/assemblies/pycore/WrpInterop.GroupDocs.PyCore.dll
groupdocs/assemblies/pydrawing/Microsoft.Win32.SystemEvents.dll
groupdocs/assemblies/pydrawing/System.Drawing.Common.dll
groupdocs/assemblies/pydrawing/WrpInterop.GroupDocs.PyDrawing.dll
groupdocs/assemblies/pygc/GroupDocs.PyGC.dll
groupdocs/assemblies/pyreflection/WrpInterop.GroupDocs.PyReflection.dll
groupdocs/assemblies/viewer/GroupDocs.Viewer.dll
groupdocs/assemblies/viewer/Microsoft.DotNet.PlatformAbstractions.dll
groupdocs/assemblies/viewer/Microsoft.Extensions.DependencyModel.dll
groupdocs/assemblies/viewer/Microsoft.Extensions.Logging.Abstractions.dll
groupdocs/assemblies/viewer/Microsoft.Win32.SystemEvents.dll
GroupDocs.Viewer-24.5.dist-info/METADATA
GroupDocs.Viewer-24.5.dist-info/WHEEL
GroupDocs.Viewer-24.5.dist-info/entry_points.txt
GroupDocs.Viewer-24.5.dist-info/top_level.txt
GroupDocs.Viewer-24.5.dist-info/RECORD
