Metadata-Version: 2.1
Name: GroupDocs.Viewer
Version: 24.5
Summary: GroupDocs.Viewer for Python via .NET is a robust document viewer API that supports over 180 file types and enables developers to easily render files to various formats, such as PDF, HTML, JPG, or PNG.
Home-page: https://products.groupdocs.com/viewer
Author: GroupDocs
License: Other/Proprietary License
Keywords: viewer,view,file,render,api,pdf,docx,xlsx,pptx,html,png,word,excel,powerpoint,visio,opendocument,photoshop
Platform: win32
Classifier: Operating System :: Microsoft :: Windows
Classifier: Operating System :: POSIX :: Linux
Classifier: Operating System :: Unix
Classifier: License :: Other/Proprietary License
Classifier: Programming Language :: Python :: 3
Classifier: Programming Language :: Python :: 3 :: Only
Classifier: Programming Language :: Python :: 3.8
Classifier: Programming Language :: Python :: 3.9
Classifier: Topic :: Multimedia :: Graphics :: Viewers
Classifier: Topic :: Software Development :: Libraries
Classifier: Topic :: Utilities
Requires-Python: >=3.5,<3.12
